passagemath_ppl.libs/libgmp-8428206e.so.10.5.0
passagemath_ppl.libs/libgmpxx-77d3dd90.so.4.7.0
passagemath_ppl.libs/libppl-525aa236.so.14.0.0
ppl/__init__.py
ppl/bit_arrays.cpython-314-i386-linux-gnu.so
ppl/bit_arrays.pxd
ppl/congruence.cpython-314-i386-linux-gnu.so
ppl/congruence.pxd
ppl/constraint.cpython-314-i386-linux-gnu.so
ppl/constraint.pxd
ppl/generator.cpython-314-i386-linux-gnu.so
ppl/generator.pxd
ppl/linear_algebra.cpython-314-i386-linux-gnu.so
ppl/linear_algebra.pxd
ppl/mip_problem.cpython-314-i386-linux-gnu.so
ppl/mip_problem.pxd
ppl/polyhedron.cpython-314-i386-linux-gnu.so
ppl/polyhedron.pxd
ppl/ppl_decl.pxd
ppl/ppl_shim.hh
passagemath_ppl-0.8.10.2.dist-info/METADATA
passagemath_ppl-0.8.10.2.dist-info/WHEEL
passagemath_ppl-0.8.10.2.dist-info/top_level.txt
passagemath_ppl-0.8.10.2.dist-info/RECORD
passagemath_ppl-0.8.10.2.dist-info/licenses/LICENSE.txt
