Metadata-Version: 2.4
Name: passagemath-ppl
Version: 0.8.10.2
Summary: Python wrapper for the Parma Polyhedra Library (pplpy fork)
Author-email: Vincent Delecroix <vincent.delecroix@labri.fr>
Maintainer: Matthias Köppe, passagemath contributors
License: GPL v3
Project-URL: Repo (upstream), https://github.com/sagemath/pplpy
Project-URL: Repo, https://github.com/passagemath/passagemath-ppl
Keywords: polyhedron,polytope,convex,mathematics,ppl,milp,linear-programming
Platform: any
Classifier: License :: OSI Approved :: GNU General Public License v3 (GPLv3)
Classifier: Programming Language :: C++
Classifier: Programming Language :: Python
Classifier: Development Status :: 5 - Production/Stable
Classifier: Operating System :: Unix
Classifier: Intended Audience :: Science/Research
Classifier: Programming Language :: Python :: 3.8
Classifier: Programming Language :: Python :: 3.9
Classifier: Programming Language :: Python :: 3.10
Classifier: Programming Language :: Python :: 3.11
Classifier: Programming Language :: Python :: 3.12
Classifier: Programming Language :: Python :: 3.13
License-File: LICENSE.txt
Requires-Dist: cysignals
Requires-Dist: gmpy2>=2.1.0b1
Provides-Extra: doc
Requires-Dist: sphinx; extra == "doc"
Dynamic: license-file
